setup.py
telegram.py
tgb.egg-info/PKG-INFO
tgb.egg-info/SOURCES.txt
tgb.egg-info/dependency_links.txt
tgb.egg-info/requires.txt
tgb.egg-info/top_level.txt