Metadata-Version: 1.0
Name: tgb
Version: 1.2.0
Summary: A minimal Telegram API wrappper
Home-page: https://github.com/banteg/telegram
Author: UNKNOWN
Author-email: UNKNOWN
License: UNKNOWN
Platform: UNKNOWN
